Hardware_simulation/kalman_anc_core.v
`timescale 1ns / 1ps

// ==============================================================================
// MAC Unit (Multiply-Accumulate) for Fixed-Point Q15.16
// ==============================================================================
module mac_unit #(
    parameter D_WIDTH = 32,
    parameter Q_FRAC = 16
)(
    input wire clk,
    input wire rst_n,
    input wire clear,
    input wire en,
    input wire signed [D_WIDTH-1:0] a,
    input wire signed [D_WIDTH-1:0] b,
    output reg signed [D_WIDTH-1:0] accum
);
    wire signed [2*D_WIDTH-1:0] mult_result;
    assign mult_result = (a * b) >>> Q_FRAC;

    always @(posedge clk or negedge rst_n) begin
        if (!rst_n) begin
            accum <= 0;
        end else if (clear) begin
            accum <= 0;
        end else if (en) begin
            accum <= accum + mult_result[D_WIDTH-1:0]; 
        end
    end
endmodule

// ==============================================================================
// Behavioral Divider (Placeholder for standard IP Core)
// ==============================================================================
module behavioral_divider #(
    parameter D_WIDTH = 32,
    parameter Q_FRAC = 16
)(
    input wire clk,
    input wire rst_n,
    input wire start,
    input wire signed [D_WIDTH-1:0] num,
    input wire signed [D_WIDTH-1:0] den,
    output reg signed [D_WIDTH-1:0] quotient,
    output reg done
);
    // Note: In a real FPGA, replace this with a DSP Divider Generator IP
    // taking multiple clock cycles. This behavioral model takes 1 cycle.
    always @(posedge clk or negedge rst_n) begin
        if (!rst_n) begin
            quotient <= 0;
            done <= 0;
        end else if (start) begin
            if (den != 0) begin
                // Shift numerator for fixed-point division
                quotient <= (num <<< Q_FRAC) / den; 
            end else begin
                quotient <= 0; // Avoid divide by zero
            end
            done <= 1;
        end else begin
            done <= 0;
        end
    end
endmodule

// ==============================================================================
// Main Kalman Filter ANC Core
// ==============================================================================
module kalman_anc_core #(
    parameter D_WIDTH = 32,
    parameter Q_FRAC = 16,
    parameter N_TAPS  = 32
)(
    input wire clk,
    input wire rst_n,
    input wire start,
    input wire signed [D_WIDTH-1:0] d_in, // Primary noise
    input wire signed [D_WIDTH-1:0] u_in, // Reference signal
    
    output reg signed [D_WIDTH-1:0] y_out, // Anti-noise
    output reg valid,
    output reg done
);

    // --------------------------------------------------------
    // Memories (Inferred BRAMs) and Registers
    // --------------------------------------------------------
    reg signed [D_WIDTH-1:0] u_buffer [0:N_TAPS-1];       // Reference delay line C(n)
    reg signed [D_WIDTH-1:0] x_state [0:N_TAPS-1];        // State vector x(n)
    reg signed [D_WIDTH-1:0] K_cov [0:N_TAPS-1][0:N_TAPS-1]; // Covariance Matrix K(n)
    
    reg signed [D_WIDTH-1:0] a_priori_err;
    reg signed [D_WIDTH-1:0] kalman_gain [0:N_TAPS-1];

    // Constant Noise Parameters (Adjust based on Q-format)
    localparam signed [D_WIDTH-1:0] Q1 = 32'h0000_0010; // State Noise 
    localparam signed [D_WIDTH-1:0] Q2 = 32'h0000_1999; // Measurement Noise (~0.1)

    // --------------------------------------------------------
    // FSM States
    // --------------------------------------------------------
    localparam IDLE         = 3'd0;
    localparam SHIFT_U      = 3'd1;
    localparam FILTER_OUT   = 3'd2;
    localparam DENOM_CALC   = 3'd3;
    localparam DIVIDE       = 3'd4;
    localparam GAIN_UPDATE  = 3'd5;
    localparam STATE_UPDATE = 3'd6;
    localparam COV_UPDATE   = 3'd7;

    reg [2:0] current_state, next_state;
    reg [5:0] row_cnt, col_cnt;

    // --------------------------------------------------------
    // Datapath Control Signals
    // --------------------------------------------------------
    reg mac_clear, mac_en;
    reg signed [D_WIDTH-1:0] mac_a, mac_b;
    wire signed [D_WIDTH-1:0] mac_accum;
    
    reg div_start;
    wire signed [D_WIDTH-1:0] div_quotient;
    wire div_done;

    // Instantiations
    mac_unit #(.D_WIDTH(D_WIDTH), .Q_FRAC(Q_FRAC)) MAC (
        .clk(clk), .rst_n(rst_n), .clear(mac_clear), .en(mac_en),
        .a(mac_a), .b(mac_b), .accum(mac_accum)
    );

    behavioral_divider #(.D_WIDTH(D_WIDTH), .Q_FRAC(Q_FRAC)) DIV (
        .clk(clk), .rst_n(rst_n), .start(div_start),
        .num(32'h0001_0000), .den(mac_accum + Q2), // 1.0 / (denom + Q2)
        .quotient(div_quotient), .done(div_done)
    );

    // --------------------------------------------------------
    // State Transition Logic
    // --------------------------------------------------------
    always @(posedge clk or negedge rst_n) begin
        if (!rst_n) current_state <= IDLE;
        else current_state <= next_state;
    end

    always @(*) begin
        next_state = current_state;
        case (current_state)
            IDLE:         if (start) next_state = SHIFT_U;
            SHIFT_U:      next_state = FILTER_OUT;
            FILTER_OUT:   if (row_cnt == N_TAPS - 1) next_state = DENOM_CALC;
            DENOM_CALC:   if (row_cnt == N_TAPS - 1 && col_cnt == N_TAPS - 1) next_state = DIVIDE;
            DIVIDE:       if (div_done) next_state = GAIN_UPDATE;
            GAIN_UPDATE:  if (row_cnt == N_TAPS - 1) next_state = STATE_UPDATE;
            STATE_UPDATE: if (row_cnt == N_TAPS - 1) next_state = COV_UPDATE;
            COV_UPDATE:   if (row_cnt == N_TAPS - 1 && col_cnt == N_TAPS - 1) next_state = IDLE;
        endcase
    end

    // --------------------------------------------------------
    // Datapath Execution
    // --------------------------------------------------------
    integer i, j;

    always @(posedge clk or negedge rst_n) begin
        if (!rst_n) begin
            row_cnt <= 0; col_cnt <= 0;
            valid <= 0; done <= 0; y_out <= 0;
            mac_clear <= 1; mac_en <= 0; div_start <= 0;
            
            for (i = 0; i < N_TAPS; i = i + 1) begin
                u_buffer[i] <= 0;
                x_state[i] <= 0;
                kalman_gain[i] <= 0;
                for (j = 0; j < N_TAPS; j = j + 1) begin
                    K_cov[i][j] <= (i == j) ? 32'h0001_0000 : 0; // Init to Identity
                end
            end
        end else begin
            // Default signal states
            mac_en <= 0; 
            div_start <= 0;
            done <= 0;
            valid <= 0;

            case (current_state)
                IDLE: begin
                    row_cnt <= 0; col_cnt <= 0;
                    mac_clear <= 1;
                end

                SHIFT_U: begin
                    // Shift delay line
                    for (i = N_TAPS-1; i > 0; i = i - 1) u_buffer[i] <= u_buffer[i-1];
                    u_buffer[0] <= u_in;
                    mac_clear <= 1;
                end

                FILTER_OUT: begin
                    mac_clear <= 0;
                    mac_en <= 1;
                    mac_a <= u_buffer[row_cnt];
                    mac_b <= x_state[row_cnt];
                    
                    if (row_cnt < N_TAPS - 1) begin
                        row_cnt <= row_cnt + 1;
                    end else begin
                        row_cnt <= 0;
                        mac_clear <= 1;
                    end
                end
                
                DENOM_CALC: begin
                    // Capture filter output on first cycle of this state
                    if (row_cnt == 0 && col_cnt == 0) begin
                        y_out <= mac_accum;
                        a_priori_err <= d_in - mac_accum;
                        valid <= 1; 
                    end
                    
                    mac_clear <= 0;
                    mac_en <= 1;
                    // C(n) * K * C(n)'
                    mac_a <= u_buffer[row_cnt];
                    mac_b <= K_cov[row_cnt][col_cnt]; 
                    
                    if (col_cnt < N_TAPS - 1) begin
                        col_cnt <= col_cnt + 1;
                    end else begin
                        col_cnt <= 0;
                        if (row_cnt < N_TAPS - 1) row_cnt <= row_cnt + 1;
                        else begin
                            row_cnt <= 0;
                            div_start <= 1; // Trigger division next
                        end
                    end
                end

                DIVIDE: begin
                    mac_clear <= 1;
                    // Waiting for div_done...
                end

                GAIN_UPDATE: begin
                    // Simplifying G computation for structural demonstration
                    // In a true implementation, this uses a MAC for K*C' first, then multiplies by quotient
                    kalman_gain[row_cnt] <= div_quotient; // Placeholder mapping
                    
                    if (row_cnt < N_TAPS - 1) row_cnt <= row_cnt + 1;
                    else row_cnt <= 0;
                end

                STATE_UPDATE: begin
                    mac_clear <= 0;
                    mac_en <= 1;
                    mac_a <= kalman_gain[row_cnt];
                    mac_b <= a_priori_err;
                    
                    // x = x + G * error
                    x_state[row_cnt] <= x_state[row_cnt] + mac_accum; 
                    
                    if (row_cnt < N_TAPS - 1) row_cnt <= row_cnt + 1;
                    else begin
                        row_cnt <= 0;
                        mac_clear <= 1;
                    end
                end

                COV_UPDATE: begin
                    // K = K - G*C*K + Q1
                    // Structural mapping (Simplified for demonstration loop)
                    if (col_cnt < N_TAPS - 1) begin
                        col_cnt <= col_cnt + 1;
                    end else begin
                        col_cnt <= 0;
                        if (row_cnt < N_TAPS - 1) begin
                            row_cnt <= row_cnt + 1;
                        end else begin
                            row_cnt <= 0;
                            done <= 1;
                        end
                    end
                end
            endcase
        end
    end
endmodule

Hardware_simulation/tb_kalman.v
`timescale 1ns / 1ps

module tb_kalman;

    // Parameters
    parameter D_WIDTH = 32;
    parameter N_TAPS  = 32;

    // Inputs
    reg clk;
    reg rst_n;
    reg start;
    reg signed [D_WIDTH-1:0] d_in;
    reg signed [D_WIDTH-1:0] u_in;

    // Outputs
    wire signed [D_WIDTH-1:0] y_out;
    wire valid;
    wire done;

    // Instantiate the Unit Under Test (UUT)
    kalman_anc_core #(
        .D_WIDTH(D_WIDTH),
        .N_TAPS(N_TAPS)
    ) uut (
        .clk(clk), 
        .rst_n(rst_n), 
        .start(start), 
        .d_in(d_in), 
        .u_in(u_in), 
        .y_out(y_out), 
        .valid(valid), 
        .done(done)
    );

    // Clock generation (100 MHz)
    always #5 clk = ~clk;

    initial begin
        // 1. Tell Icarus to dump signals for GTKWave
        $dumpfile("kalman_waves.vcd");
        $dumpvars(0, tb_kalman); // Dump all variables in this module and below

        // 2. Initialize Inputs
        clk = 0;
        rst_n = 0;
        start = 0;
        d_in = 0;
        u_in = 0;

        // 3. Release Reset
        #20;
        rst_n = 1;
        #20;

        // 4. Simulate a few sample cycles
        // Sample 1
        @(posedge clk);
        start = 1;
        d_in = 32'h0000_1000; // Dummy fixed-point data
        u_in = 32'h0000_0800;
        @(posedge clk);
        start = 0;
        
        // Wait for the FSM to finish processing the sample
        wait(done == 1);
        
        // Delay before next sample (simulating sample rate)
        #100; 

        // Sample 2
        @(posedge clk);
        start = 1;
        d_in = -32'h0000_0500;
        u_in = 32'h0000_0200;
        @(posedge clk);
        start = 0;
        
        wait(done == 1);
        
        #200;
        
        // 5. End simulation
        $display("Simulation Complete.");
        $finish;
    end
endmodule

Hardware_simulation/kalman_waves.vcd
$date
	Mon Jun 29 00:27:42 2026
$end
$version
	Icarus Verilog
$end
$timescale
	1ps
$end
$scope module tb_kalman $end
$var wire 32 ! y_out [31:0] $end
$var wire 1 " valid $end
$var wire 1 # done $end
$var reg 1 $ clk $end
$var reg 32 % d_in [31:0] $end
$var reg 1 & rst_n $end
$var reg 1 ' start $end
$var reg 32 ( u_in [31:0] $end
$scope module uut $end
$var wire 1 $ clk $end
$var wire 32 ) d_in [31:0] $end
$var wire 1 & rst_n $end
$var wire 1 ' start $end
$var wire 32 * u_in [31:0] $end
$var wire 32 + mac_accum [31:0] $end
$var wire 32 , div_quotient [31:0] $end
$var wire 1 - div_done $end
$var reg 32 . a_priori_err [31:0] $end
$var reg 6 / col_cnt [5:0] $end
$var reg 3 0 current_state [2:0] $end
$var reg 1 1 div_start $end
$var reg 1 # done $end
$var reg 32 2 mac_a [31:0] $end
$var reg 32 3 mac_b [31:0] $end
$var reg 1 4 mac_clear $end
$var reg 1 5 mac_en $end
$var reg 3 6 next_state [2:0] $end
$var reg 6 7 row_cnt [5:0] $end
$var reg 1 " valid $end
$var reg 32 8 y_out [31:0] $end
$var integer 32 9 i [31:0] $end
$var integer 32 : j [31:0] $end
$scope module DIV $end
$var wire 1 $ clk $end
$var wire 32 ; den [31:0] $end
$var wire 32 < num [31:0] $end
$var wire 1 & rst_n $end
$var wire 1 1 start $end
$var reg 1 - done $end
$var reg 32 = quotient [31:0] $end
$upscope $end
$scope module MAC $end
$var wire 32 > a [31:0] $end
$var wire 32 ? b [31:0] $end
$var wire 1 4 clear $end
$var wire 1 $ clk $end
$var wire 1 5 en $end
$var wire 1 & rst_n $end
$var wire 64 @ mult_result [63:0] $end
$var reg 32 A accum [31:0] $end
$upscope $end
$upscope $end
$upscope $end
$enddefinitions $end
#0
$dumpvars
b0 A
bx @
bx ?
bx >
b0 =
b10000000000000000 <
b1100110011001 ;
b100000 :
b100000 9
b0 8
b0 7
b0 6
05
14
bx 3
bx 2
01
b0 0
b0 /
bx .
0-
b0 ,
b0 +
b0 *
b0 )
b0 (
0'
0&
b0 %
0$
0#
0"
b0 !
$end
#5000
b100000 :
b100000 9
1$
#10000
0$
#15000
b100000 :
b100000 9
1$
#20000
0$
1&
#25000
1$
#30000
0$
#35000
1$
#40000
0$
#45000
b1 6
b100000000000 (
b100000000000 *
b1000000000000 %
b1000000000000 )
1'
1$
#50000
0$
#55000
b1 0
b10 6
0'
1$
#60000
0$
#65000
b10 0
b0 9
1$
#70000
0$
#75000
b0 @
b1 7
b0 3
b0 ?
b100000000000 2
b100000000000 >
15
04
1$
#80000
0$
#85000
b10 7
b0 2
b0 >
15
1$
#90000
0$
#95000
b11 7
15
1$
#100000
0$
#105000
b100 7
15
1$
#110000
0$
#115000
b101 7
15
1$
#120000
0$
#125000
b110 7
15
1$
#130000
0$
#135000
b111 7
15
1$
#140000
0$
#145000
b1000 7
15
1$
#150000
0$
#155000
b1001 7
15
1$
#160000
0$
#165000
b1010 7
15
1$
#170000
0$
#175000
b1011 7
15
1$
#180000
0$
#185000
b1100 7
15
1$
#190000
0$
#195000
b1101 7
15
1$
#200000
0$
#205000
b1110 7
15
1$
#210000
0$
#215000
b1111 7
15
1$
#220000
0$
#225000
b10000 7
15
1$
#230000
0$
#235000
b10001 7
15
1$
#240000
0$
#245000
b10010 7
15
1$
#250000
0$
#255000
b10011 7
15
1$
#260000
0$
#265000
b10100 7
15
1$
#270000
0$
#275000
b10101 7
15
1$
#280000
0$
#285000
b10110 7
15
1$
#290000
0$
#295000
b10111 7
15
1$
#300000
0$
#305000
b11000 7
15
1$
#310000
0$
#315000
b11001 7
15
1$
#320000
0$
#325000
b11010 7
15
1$
#330000
0$
#335000
b11011 7
15
1$
#340000
0$
#345000
b11100 7
15
1$
#350000
0$
#355000
b11101 7
15
1$
#360000
0$
#365000
b11110 7
15
1$
#370000
0$
#375000
b11 6
b11111 7
15
1$
#380000
0$
#385000
14
b0 7
15
b11 0
1$
#390000
0$
#395000
b100000000000 @
b1 /
b10000000000000000 3
b10000000000000000 ?
b100000000000 2
b100000000000 >
04
1"
b1000000000000 .
15
1$
#400000
0$
#405000
b0 @
b10 /
b0 3
b0 ?
0"
15
b10000110011001 ;
b100000000000 +
b100000000000 A
1$
#410000
0$
#415000
b11 /
15
1$
#420000
0$
#425000
b100 /
15
1$
#430000
0$
#435000
b101 /
15
1$
#440000
0$
#445000
b110 /
15
1$
#450000
0$
#455000
b111 /
15
1$
#460000
0$
#465000
b1000 /
15
1$
#470000
0$
#475000
b1001 /
15
1$
#480000
0$
#485000
b1010 /
15
1$
#490000
0$
#495000
b1011 /
15
1$
#500000
0$
#505000
b1100 /
15
1$
#510000
0$
#515000
b1101 /
15
1$
#520000
0$
#525000
b1110 /
15
1$
#530000
0$
#535000
b1111 /
15
1$
#540000
0$
#545000
b10000 /
15
1$
#550000
0$
#555000
b10001 /
15
1$
#560000
0$
#565000
b10010 /
15
1$
#570000
0$
#575000
b10011 /
15
1$
#580000
0$
#585000
b10100 /
15
1$
#590000
0$
#595000
b10101 /
15
1$
#600000
0$
#605000
b10110 /
15
1$
#610000
0$
#615000
b10111 /
15
1$
#620000
0$
#625000
b11000 /
15
1$
#630000
0$
#635000
b11001 /
15
1$
#640000
0$
#645000
b11010 /
15
1$
#650000
0$
#655000
b11011 /
15
1$
#660000
0$
#665000
b11100 /
15
1$
#670000
0$
#675000
b11101 /
15
1$
#680000
0$
#685000
b11110 /
15
1$
#690000
0$
#695000
b11111 /
15
1$
#700000
0$
#705000
b1 7
b0 /
15
1$
#710000
0$
#715000
b1 /
b0 2
b0 >
15
1$
#720000
0$
#725000
b10 /
b10000000000000000 3
b10000000000000000 ?
15
1$
#730000
0$
#735000
b11 /
b0 3
b0 ?
15
1$
#740000
0$
#745000
b100 /
15
1$
#750000
0$
#755000
b101 /
15
1$
#760000
0$
#765000
b110 /
15
1$
#770000
0$
#775000
b111 /
15
1$
#780000
0$
#785000
b1000 /
15
1$
#790000
0$
#795000
b1001 /
15
1$
#800000
0$
#805000
b1010 /
15
1$
#810000
0$
#815000
b1011 /
15
1$
#820000
0$
#825000
b1100 /
15
1$
#830000
0$
#835000
b1101 /
15
1$
#840000
0$
#845000
b1110 /
15
1$
#850000
0$
#855000
b1111 /
15
1$
#860000
0$
#865000
b10000 /
15
1$
#870000
0$
#875000
b10001 /
15
1$
#880000
0$
#885000
b10010 /
15
1$
#890000
0$
#895000
b10011 /
15
1$
#900000
0$
#905000
b10100 /
15
1$
#910000
0$
#915000
b10101 /
15
1$
#920000
0$
#925000
b10110 /
15
1$
#930000
0$
#935000
b10111 /
15
1$
#940000
0$
#945000
b11000 /
15
1$
#950000
0$
#955000
b11001 /
15
1$
#960000
0$
#965000
b11010 /
15
1$
#970000
0$
#975000
b11011 /
15
1$
#980000
0$
#985000
b11100 /
15
1$
#990000
0$
#995000
b11101 /
15
1$
#1000000
0$
#1005000
b11110 /
15
1$
#1010000
0$
#1015000
b11111 /
15
1$
#1020000
0$
#1025000
b10 7
b0 /
15
1$
#1030000
0$
#1035000
b1 /
15
1$
#1040000
0$
#1045000
b10 /
15
1$
#1050000
0$
#1055000
b11 /
b10000000000000000 3
b10000000000000000 ?
15
1$
#1060000
0$
#1065000
b100 /
b0 3
b0 ?
15
1$
#1070000
0$
#1075000
b101 /
15
1$
#1080000
0$
#1085000
b110 /
15
1$
#1090000
0$
#1095000
b111 /
15
1$
#1100000
0$
#1105000
b1000 /
15
1$
#1110000
0$
#1115000
b1001 /
15
1$
#1120000
0$
#1125000
b1010 /
15
1$
#1130000
0$
#1135000
b1011 /
15
1$
#1140000
0$
#1145000
b1100 /
15
1$
#1150000
0$
#1155000
b1101 /
15
1$
#1160000
0$
#1165000
b1110 /
15
1$
#1170000
0$
#1175000
b1111 /
15
1$
#1180000
0$
#1185000
b10000 /
15
1$
#1190000
0$
#1195000
b10001 /
15
1$
#1200000
0$
#1205000
b10010 /
15
1$
#1210000
0$
#1215000
b10011 /
15
1$
#1220000
0$
#1225000
b10100 /
15
1$
#1230000
0$
#1235000
b10101 /
15
1$
#1240000
0$
#1245000
b10110 /
15
1$
#1250000
0$
#1255000
b10111 /
15
1$
#1260000
0$
#1265000
b11000 /
15
1$
#1270000
0$
#1275000
b11001 /
15
1$
#1280000
0$
#1285000
b11010 /
15
1$
#1290000
0$
#1295000
b11011 /
15
1$
#1300000
0$
#1305000
b11100 /
15
1$
#1310000
0$
#1315000
b11101 /
15
1$
#1320000
0$
#1325000
b11110 /
15
1$
#1330000
0$
#1335000
b11111 /
15
1$
#1340000
0$
#1345000
b11 7
b0 /
15
1$
#1350000
0$
#1355000
b1 /
15
1$
#1360000
0$
#1365000
b10 /
15
1$
#1370000
0$
#1375000
b11 /
15
1$
#1380000
0$
#1385000
b100 /
b10000000000000000 3
b10000000000000000 ?
15
1$
#1390000
0$
#1395000
b101 /
b0 3
b0 ?
15
1$
#1400000
0$
#1405000
b110 /
15
1$
#1410000
0$
#1415000
b111 /
15
1$
#1420000
0$
#1425000
b1000 /
15
1$
#1430000
0$
#1435000
b1001 /
15
1$
#1440000
0$
#1445000
b1010 /
15
1$
#1450000
0$
#1455000
b1011 /
15
1$
#1460000
0$
#1465000
b1100 /
15
1$
#1470000
0$
#1475000
b1101 /
15
1$
#1480000
0$
#1485000
b1110 /
15
1$
#1490000
0$
#1495000
b1111 /
15
1$
#1500000
0$
#1505000
b10000 /
15
1$
#1510000
0$
#1515000
b10001 /
15
1$
#1520000
0$
#1525000
b10010 /
15
1$
#1530000
0$
#1535000
b10011 /
15
1$
#1540000
0$
#1545000
b10100 /
15
1$
#1550000
0$
#1555000
b10101 /
15
1$
#1560000
0$
#1565000
b10110 /
15
1$
#1570000
0$
#1575000
b10111 /
15
1$
#1580000
0$
#1585000
b11000 /
15
1$
#1590000
0$
#1595000
b11001 /
15
1$
#1600000
0$
#1605000
b11010 /
15
1$
#1610000
0$
#1615000
b11011 /
15
1$
#1620000
0$
#1625000
b11100 /
15
1$
#1630000
0$
#1635000
b11101 /
15
1$
#1640000
0$
#1645000
b11110 /
15
1$
#1650000
0$
#1655000
b11111 /
15
1$
#1660000
0$
#1665000
b100 7
b0 /
15
1$
#1670000
0$
#1675000
b1 /
15
1$
#1680000
0$
#1685000
b10 /
15
1$
#1690000
0$
#1695000
b11 /
15
1$
#1700000
0$
#1705000
b100 /
15
1$
#1710000
0$
#1715000
b101 /
b10000000000000000 3
b10000000000000000 ?
15
1$
#1720000
0$
#1725000
b110 /
b0 3
b0 ?
15
1$
#1730000
0$
#1735000
b111 /
15
1$
#1740000
0$
#1745000
b1000 /
15
1$
#1750000
0$
#1755000
b1001 /
15
1$
#1760000
0$
#1765000
b1010 /
15
1$
#1770000
0$
#1775000
b1011 /
15
1$
#1780000
0$
#1785000
b1100 /
15
1$
#1790000
0$
#1795000
b1101 /
15
1$
#1800000
0$
#1805000
b1110 /
15
1$
#1810000
0$
#1815000
b1111 /
15
1$
#1820000
0$
#1825000
b10000 /
15
1$
#1830000
0$
#1835000
b10001 /
15
1$
#1840000
0$
#1845000
b10010 /
15
1$
#1850000
0$
#1855000
b10011 /
15
1$
#1860000
0$
#1865000
b10100 /
15
1$
#1870000
0$
#1875000
b10101 /
15
1$
#1880000
0$
#1885000
b10110 /
15
1$
#1890000
0$
#1895000
b10111 /
15
1$
#1900000
0$
#1905000
b11000 /
15
1$
#1910000
0$
#1915000
b11001 /
15
1$
#1920000
0$
#1925000
b11010 /
15
1$
#1930000
0$
#1935000
b11011 /
15
1$
#1940000
0$
#1945000
b11100 /
15
1$
#1950000
0$
#1955000
b11101 /
15
1$
#1960000
0$
#1965000
b11110 /
15
1$
#1970000
0$
#1975000
b11111 /
15
1$
#1980000
0$
#1985000
b101 7
b0 /
15
1$
#1990000
0$
#1995000
b1 /
15
1$
#2000000
0$
#2005000
b10 /
15
1$
#2010000
0$
#2015000
b11 /
15
1$
#2020000
0$
#2025000
b100 /
15
1$
#2030000
0$
#2035000
b101 /
15
1$
#2040000
0$
#2045000
b110 /
b10000000000000000 3
b10000000000000000 ?
15
1$
#2050000
0$
#2055000
b111 /
b0 3
b0 ?
15
1$
#2060000
0$
#2065000
b1000 /
15
1$
#2070000
0$
#2075000
b1001 /
15
1$
#2080000
0$
#2085000
b1010 /
15
1$
#2090000
0$
#2095000
b1011 /
15
1$
#2100000
0$
#2105000
b1100 /
15
1$
#2110000
0$
#2115000
b1101 /
15
1$
#2120000
0$
#2125000
b1110 /
15
1$
#2130000
0$
#2135000
b1111 /
15
1$
#2140000
0$
#2145000
b10000 /
15
1$
#2150000
0$
#2155000
b10001 /
15
1$
#2160000
0$
#2165000
b10010 /
15
1$
#2170000
0$
#2175000
b10011 /
15
1$
#2180000
0$
#2185000
b10100 /
15
1$
#2190000
0$
#2195000
b10101 /
15
1$
#2200000
0$
#2205000
b10110 /
15
1$
#2210000
0$
#2215000
b10111 /
15
1$
#2220000
0$
#2225000
b11000 /
15
1$
#2230000
0$
#2235000
b11001 /
15
1$
#2240000
0$
#2245000
b11010 /
15
1$
#2250000
0$
#2255000
b11011 /
15
1$
#2260000
0$
#2265000
b11100 /
15
1$
#2270000
0$
#2275000
b11101 /
15
1$
#2280000
0$
#2285000
b11110 /
15
1$
#2290000
0$
#2295000
b11111 /
15
1$
#2300000
0$
#2305000
b110 7
b0 /
15
1$
#2310000
0$
#2315000
b1 /
15
1$
#2320000
0$
#2325000
b10 /
15
1$
#2330000
0$
#2335000
b11 /
15
1$
#2340000
0$
#2345000
b100 /
15
1$
#2350000
0$
#2355000
b101 /
15
1$
#2360000
0$
#2365000
b110 /
15
1$
#2370000
0$
#2375000
b111 /
b10000000000000000 3
b10000000000000000 ?
15
1$
#2380000
0$
#2385000
b1000 /
b0 3
b0 ?
15
1$
#2390000
0$
#2395000
b1001 /
15
1$
#2400000
0$
#2405000
b1010 /
15
1$
#2410000
0$
#2415000
b1011 /
15
1$
#2420000
0$
#2425000
b1100 /
15
1$
#2430000
0$
#2435000
b1101 /
15
1$
#2440000
0$
#2445000
b1110 /
15
1$
#2450000
0$
#2455000
b1111 /
15
1$
#2460000
0$
#2465000
b10000 /
15
1$
#2470000
0$
#2475000
b10001 /
15
1$
#2480000
0$
#2485000
b10010 /
15
1$
#2490000
0$
#2495000
b10011 /
15
1$
#2500000
0$
#2505000
b10100 /
15
1$
#2510000
0$
#2515000
b10101 /
15
1$
#2520000
0$
#2525000
b10110 /
15
1$
#2530000
0$
#2535000
b10111 /
15
1$
#2540000
0$
#2545000
b11000 /
15
1$
#2550000
0$
#2555000
b11001 /
15
1$
#2560000
0$
#2565000
b11010 /
15
1$
#2570000
0$
#2575000
b11011 /
15
1$
#2580000
0$
#2585000
b11100 /
15
1$
#2590000
0$
#2595000
b11101 /
15
1$
#2600000
0$
#2605000
b11110 /
15
1$
#2610000
0$
#2615000
b11111 /
15
1$
#2620000
0$
#2625000
b111 7
b0 /
15
1$
#2630000
0$
#2635000
b1 /
15
1$
#2640000
0$
#2645000
b10 /
15
1$
#2650000
0$
#2655000
b11 /
15
1$
#2660000
0$
#2665000
b100 /
15
1$
#2670000
0$
#2675000
b101 /
15
1$
#2680000
0$
#2685000
b110 /
15
1$
#2690000
0$
#2695000
b111 /
15
1$
#2700000
0$
#2705000
b1000 /
b10000000000000000 3
b10000000000000000 ?
15
1$
#2710000
0$
#2715000
b1001 /
b0 3
b0 ?
15
1$
#2720000
0$
#2725000
b1010 /
15
1$
#2730000
0$
#2735000
b1011 /
15
1$
#2740000
0$
#2745000
b1100 /
15
1$
#2750000
0$
#2755000
b1101 /
15
1$
#2760000
0$
#2765000
b1110 /
15
1$
#2770000
0$
#2775000
b1111 /
15
1$
#2780000
0$
#2785000
b10000 /
15
1$
#2790000
0$
#2795000
b10001 /
15
1$
#2800000
0$
#2805000
b10010 /
15
1$
#2810000
0$
#2815000
b10011 /
15
1$
#2820000
0$
#2825000
b10100 /
15
1$
#2830000
0$
#2835000
b10101 /
15
1$
#2840000
0$
#2845000
b10110 /
15
1$
#2850000
0$
#2855000
b10111 /
15
1$
#2860000
0$
#2865000
b11000 /
15
1$
#2870000
0$
#2875000
b11001 /
15
1$
#2880000
0$
#2885000
b11010 /
15
1$
#2890000
0$
#2895000
b11011 /
15
1$
#2900000
0$
#2905000
b11100 /
15
1$
#2910000
0$
#2915000
b11101 /
15
1$
#2920000
0$
#2925000
b11110 /
15
1$
#2930000
0$
#2935000
b11111 /
15
1$
#2940000
0$
#2945000
b1000 7
b0 /
15
1$
#2950000
0$
#2955000
b1 /
15
1$
#2960000
0$
#2965000
b10 /
15
1$
#2970000
0$
#2975000
b11 /
15
1$
#2980000
0$
#2985000
b100 /
15
1$
#2990000
0$
#2995000
b101 /
15
1$
#3000000
0$
#3005000
b110 /
15
1$
#3010000
0$
#3015000
b111 /
15
1$
#3020000
0$
#3025000
b1000 /
15
1$
#3030000
0$
#3035000
b1001 /
b10000000000000000 3
b10000000000000000 ?
15
1$
#3040000
0$
#3045000
b1010 /
b0 3
b0 ?
15
1$
#3050000
0$
#3055000
b1011 /
15
1$
#3060000
0$
#3065000
b1100 /
15
1$
#3070000
0$
#3075000
b1101 /
15
1$
#3080000
0$
#3085000
b1110 /
15
1$
#3090000
0$
#3095000
b1111 /
15
1$
#3100000
0$
#3105000
b10000 /
15
1$
#3110000
0$
#3115000
b10001 /
15
1$
#3120000
0$
#3125000
b10010 /
15
1$
#3130000
0$
#3135000
b10011 /
15
1$
#3140000
0$
#3145000
b10100 /
15
1$
#3150000
0$
#3155000
b10101 /
15
1$
#3160000
0$
#3165000
b10110 /
15
1$
#3170000
0$
#3175000
b10111 /
15
1$
#3180000
0$
#3185000
b11000 /
15
1$
#3190000
0$
#3195000
b11001 /
15
1$
#3200000
0$
#3205000
b11010 /
15
1$
#3210000
0$
#3215000
b11011 /
15
1$
#3220000
0$
#3225000
b11100 /
15
1$
#3230000
0$
#3235000
b11101 /
15
1$
#3240000
0$
#3245000
b11110 /
15
1$
#3250000
0$
#3255000
b11111 /
15
1$
#3260000
0$
#3265000
b1001 7
b0 /
15
1$
#3270000
0$
#3275000
b1 /
15
1$
#3280000
0$
#3285000
b10 /
15
1$
#3290000
0$
#3295000
b11 /
15
1$
#3300000
0$
#3305000
b100 /
15
1$
#3310000
0$
#3315000
b101 /
15
1$
#3320000
0$
#3325000
b110 /
15
1$
#3330000
0$
#3335000
b111 /
15
1$
#3340000
0$
#3345000
b1000 /
15
1$
#3350000
0$
#3355000
b1001 /
15
1$
#3360000
0$
#3365000
b1010 /
b10000000000000000 3
b10000000000000000 ?
15
1$
#3370000
0$
#3375000
b1011 /
b0 3
b0 ?
15
1$
#3380000
0$
#3385000
b1100 /
15
1$
#3390000
0$
#3395000
b1101 /
15
1$
#3400000
0$
#3405000
b1110 /
15
1$
#3410000
0$
#3415000
b1111 /
15
1$
#3420000
0$
#3425000
b10000 /
15
1$
#3430000
0$
#3435000
b10001 /
15
1$
#3440000
0$
#3445000
b10010 /
15
1$
#3450000
0$
#3455000
b10011 /
15
1$
#3460000
0$
#3465000
b10100 /
15
1$
#3470000
0$
#3475000
b10101 /
15
1$
#3480000
0$
#3485000
b10110 /
15
1$
#3490000
0$
#3495000
b10111 /
15
1$
#3500000
0$
#3505000
b11000 /
15
1$
#3510000
0$
#3515000
b11001 /
15
1$
#3520000
0$
#3525000
b11010 /
15
1$
#3530000
0$
#3535000
b11011 /
15
1$
#3540000
0$
#3545000
b11100 /
15
1$
#3550000
0$
#3555000
b11101 /
15
1$
#3560000
0$
#3565000
b11110 /
15
1$
#3570000
0$
#3575000
b11111 /
15
1$
#3580000
0$
#3585000
b1010 7
b0 /
15
1$
#3590000
0$
